CHANGELOG
LICENSE
MANIFEST.in
README.rst
setup.py
django_skwissh.egg-info/PKG-INFO
django_skwissh.egg-info/SOURCES.txt
django_skwissh.egg-info/dependency_links.txt
django_skwissh.egg-info/requires.txt
django_skwissh.egg-info/top_level.txt
skwissh/__init__.py
skwissh/admin.py
skwissh/cron.py
skwissh/fields.py
skwissh/forms.py
skwissh/generic_views.py
skwissh/models.py
skwissh/settings.py
skwissh/tests.py
skwissh/urls.py
skwissh/views.py
skwissh/fixtures/initial_data.json
skwissh/locale/en/LC_MESSAGES/django.mo
skwissh/locale/fr/LC_MESSAGES/django.mo
skwissh/migrations/0001_initial.py
skwissh/migrations/__init__.py
skwissh/static/skwissh/images/foundation/orbit/left-arrow-small.png
skwissh/static/skwissh/images/foundation/orbit/left-arrow.png
skwissh/static/skwissh/images/foundation/orbit/loading.gif
skwissh/static/skwissh/images/foundation/orbit/mask-black.png
skwissh/static/skwissh/images/foundation/orbit/pause-black.png
skwissh/static/skwissh/images/foundation/orbit/right-arrow-small.png
skwissh/static/skwissh/images/foundation/orbit/right-arrow.png
skwissh/static/skwissh/images/foundation/orbit/rotator-black.png
skwissh/static/skwissh/images/foundation/orbit/timer-black.png
skwissh/static/skwissh/images/skwissh/HTML5_Badge.svg
skwissh/static/skwissh/images/skwissh/ajax-loader.gif
skwissh/static/skwissh/images/skwissh/arrow-down.svg
skwissh/static/skwissh/images/skwissh/arrow-right.svg
skwissh/static/skwissh/images/skwissh/bargraph.svg
skwissh/static/skwissh/images/skwissh/bargraph_groups.svg
skwissh/static/skwissh/images/skwissh/delete.svg
skwissh/static/skwissh/images/skwissh/demo1.png
skwissh/static/skwissh/images/skwissh/demo2.png
skwissh/static/skwissh/images/skwissh/demo3.png
skwissh/static/skwissh/images/skwissh/demo4.png
skwissh/static/skwissh/images/skwissh/demo5.png
skwissh/static/skwissh/images/skwissh/demo6.png
skwissh/static/skwissh/images/skwissh/demo7.png
skwissh/static/skwissh/images/skwissh/demo8.png
skwissh/static/skwissh/images/skwissh/download.svg
skwissh/static/skwissh/images/skwissh/edit.svg
skwissh/static/skwissh/images/skwissh/en.svg
skwissh/static/skwissh/images/skwissh/favicon.png
