Metadata-Version: 1.1
Name: django-skwissh
Version: 0.0.8
Summary: SSH monitoring Django application
Home-page: http://skwissh.com/
Author: Roland Saikali
Author-email: contact@skwissh.com
License: GNU General Public License
Download-URL: https://github.com/rsaikali/django-skwissh
Platform: OS Independent
Classifier: Development Status :: 5 - Production/Stable
Classifier: Environment :: Web Environment
Classifier: Framework :: Django
Classifier: Intended Audience :: Developers
Classifier: Intended Audience :: System Administrators
Classifier: License :: OSI Approved :: GNU General Public License (GPL)
Classifier: Natural Language :: French
Classifier: Natural Language :: English
Classifier: Operating System :: OS Independent
Classifier: Programming Language :: Python
Classifier: Topic :: System :: Monitoring
